narmer/__init__.py
narmer/phonetic.py
narmer/stats.py
narmer-0.1.1.dist-info/WHEEL
narmer-0.1.1.dist-info/DESCRIPTION.rst
narmer-0.1.1.dist-info/METADATA
narmer-0.1.1.dist-info/RECORD
narmer-0.1.1.dist-info/metadata.json
narmer-0.1.1.dist-info/top_level.txt
