Metadata-Version: 2.0
Name: narmer
Version: 0.1.1
Summary: Narmer Experimental NLP/IR library for Python
Home-page: https://github.com/chrislit/narmer
Author: Christopher C. Little
Author-email: chrisclittle+narmer@gmail.com
License: GPLv3+
Download-URL: https://github.com/chrislit/narmer/archive/master.zip
Keywords: nlp,ai,ir,language,linguistics,phonetic algorithms
Platform: UNKNOWN
Classifier: Programming Language :: Python
Classifier: Programming Language :: Python :: 2
Classifier: Programming Language :: Python :: 2.7
Classifier: Programming Language :: Python :: 3
Classifier: Programming Language :: Python :: 3.3
Classifier: Programming Language :: Python :: 3.4
Classifier: Development Status :: 3 - Alpha
Classifier: Environment :: Other Environment
Classifier: Intended Audience :: Developers
Classifier: Operating System :: OS Independent
Classifier: License :: OSI Approved :: GNU General Public License v3 or later (GPLv3+)
Classifier: Topic :: Scientific/Engineering :: Artificial Intelligence
Classifier: Topic :: Software Development :: Libraries :: Python Modules
Classifier: Topic :: Text Processing :: Indexing
Classifier: Topic :: Text Processing :: Linguistic
Requires-Dist: abydos
